phd_ms/__init__.py
phd_ms/_utils/__init__.py
phd_ms/_utils/_benchmark.py
phd_ms/_utils/_filtration.py
phd_ms/_utils/_leiden.py
phd_ms/tools/__init__.py
phd_ms/tools/_phdms.py
phd_ms-1.1.1.dist-info/licenses/LICENSE.md
phd_ms-1.1.1.dist-info/METADATA
phd_ms-1.1.1.dist-info/WHEEL
phd_ms-1.1.1.dist-info/top_level.txt
phd_ms-1.1.1.dist-info/RECORD
