Metadata-Version: 2.4
Name: phd_ms
Version: 1.1.1
Summary: Identifying multiscale tissue domains for spatial transcriptomic data using persistent homology.
Author: Perry Beamer
License: MIT License
Keywords: multiscale domains,spatial transcriptomics,topological data analysis
Classifier: Programming Language :: Python :: 3.9
Classifier: License :: OSI Approved :: MIT License
Classifier: Operating System :: POSIX :: Linux
Classifier: Operating System :: MacOS
Classifier: Topic :: Scientific/Engineering
Classifier: Topic :: Scientific/Engineering :: Bio-Informatics
Requires-Python: >=3.7
License-File: LICENSE.md
Requires-Dist: gudhi>=3.8.0
Requires-Dist: leidenalg>=0.9.0
Requires-Dist: matplotlib==3.10.3
Requires-Dist: mpl_point_clicker
Requires-Dist: numpy>=1.23.4
Requires-Dist: pandas>=2.2.0
Requires-Dist: pot>=0.8.0
Requires-Dist: scanpy==1.11.2
Requires-Dist: scipy>=1.9.1
Requires-Dist: scikit-learn>=1.5.1
Requires-Dist: tqdm>=4.67
Requires-Dist: importlib-metadata
Dynamic: license-file
